marilyn_api/__init__.py
marilyn_api/api.py
marilyn_api/client.py
marilyn_api/exeptions.py
marilyn_api-0.1.1.dist-info/LICENSE
marilyn_api-0.1.1.dist-info/WHEEL
marilyn_api-0.1.1.dist-info/METADATA
marilyn_api-0.1.1.dist-info/RECORD
