Metadata-Version: 2.1
Name: marilyn-api
Version: 0.1.1
Summary: Async client for Marilyn API
Home-page: https://github.com/pavelmaksimov/marilyn-api
Keywords: client,api,python,marilyn
Author: pmaksimov
Author-email: vur21@ya.ru
Requires-Python: >=3.7,<4.0
Classifier: Programming Language :: Python :: 3
Classifier: Programming Language :: Python :: 3.10
Classifier: Programming Language :: Python :: 3.7
Classifier: Programming Language :: Python :: 3.8
Classifier: Programming Language :: Python :: 3.9
Requires-Dist: aiohttp (>=3.8.1,<4.0.0)
